pokers_db-2.2.dist-info/METADATA
pokers_db-2.2.dist-info/WHEEL
pokers/__init__.py
pokers/__init__.pyi
pokers/py.typed
pokers/pokers.cpython-310-darwin.so
pokers_db-2.2.dist-info/RECORD
